openseespy/LICENSE.md
openseespy/__init__.py
openseespy/opensees/__init__.py
openseespy/postprocessing/__init__.py
openseespy/preprocessing/DiscretizeMember.py
openseespy/preprocessing/__init__.py
openseespy-3.7.0.6.dist-info/METADATA
openseespy-3.7.0.6.dist-info/WHEEL
openseespy-3.7.0.6.dist-info/top_level.txt
openseespy-3.7.0.6.dist-info/RECORD
