Metadata-Version: 2.1
Name: openseespy
Version: 3.7.0.6
Summary: A OpenSeesPy package
Home-page: https://github.com/zhuminjie/openseespy
Author: Minjie Zhu
Author-email: zhum@oregonstate.edu
License: OpenSeesPy is free for research, education, and internal use. Commercial redistribution of OpenSeesPy, such as, but not limited to, an application or cloud-based service that uses import openseespy, requires a license similar to that required for commercial redistribution of OpenSees.exe. Contact Dr. Minjie Zhu (zhum@oregonstate.edu) for commercial licensing details.
Platform: Linux
Platform: Windows
Platform: Mac
Classifier: Programming Language :: Python
Classifier: Operating System :: POSIX :: Linux
Classifier: Operating System :: Microsoft :: Windows
Classifier: Operating System :: MacOS :: MacOS X
Requires-Python: >=3.9
Requires-Dist: openseespywin>=3.7.0.6; platform_system == "Windows"
Requires-Dist: openseespylinux>=3.7.0.6; platform_system == "Linux"
Requires-Dist: openseespymac>=3.4.0.2; platform_system == "Darwin"
